{
  "project_info": {
    "project_number": "208126441744",
    "project_id": "proyectoensenarte-d4dd2",
    "storage_bucket": "proyectoensenarte-d4dd2.appspot.com"
  },
  "client": [
    {
      "client_info": {
        "mobilesdk_app_id": "1:208126441744:android:293c157376986889888d95",
        "android_client_info": {
          "package_name": "com.puj.proyectoensenarte"
        }
      },
      "oauth_client": [],
      "api_key": [
        {
          "current_key": "AIzaSyC2YozqJ8MkYVVbuQb14AfgO9f-yXQLNto"
        }
      ],
      "services": {
        "appinvite_service": {
          "other_platform_oauth_client": []
        }
      }
    }
  ],
  "configuration_version": "1"
}